{
  "project_info": {
    "project_number": "403090252778",
    "project_id": "my-community-a5e69",
    "storage_bucket": "my-community-a5e69.appspot.com"
  },
  "client": [
    {
      "client_info": {
        "mobilesdk_app_id": "1:403090252778:android:fe39f5436dac6c848bc893",
        "android_client_info": {
          "package_name": "com.example.community"
        }
      },
      "oauth_client": [
        {
          "client_id": "403090252778-22pv9spk76snfjin64oe5v0gi8vrfmvo.apps.googleusercontent.com",
          "client_type": 3
        }
      ],
      "api_key": [
        {
          "current_key": "AIzaSyB28HXVqpNRc5UCk73VZlD32x_VCRjnZf0"
        }
      ],
      "services": {
        "appinvite_service": {
          "other_platform_oauth_client": [
            {
              "client_id": "403090252778-22pv9spk76snfjin64oe5v0gi8vrfmvo.apps.googleusercontent.com",
              "client_type": 3
            }
          ]
        }
      }
    },
    {
      "client_info": {
        "mobilesdk_app_id": "1:403090252778:android:bab680070365d0a68bc893",
        "android_client_info": {
          "package_name": "com.example.mycommunity"
        }
      },
      "oauth_client": [
        {
          "client_id": "403090252778-jnk3rmrco1vucfd2am2i8ouibh46d79u.apps.googleusercontent.com",
          "client_type": 1,
          "android_info": {
            "package_name": "com.example.mycommunity",
            "certificate_hash": "e2b3103338bede14acc8272dffb44f7b2df1ca8d"
          }
        },
        {
          "client_id": "403090252778-22pv9spk76snfjin64oe5v0gi8vrfmvo.apps.googleusercontent.com",
          "client_type": 3
        }
      ],
      "api_key": [
        {
          "current_key": "AIzaSyB28HXVqpNRc5UCk73VZlD32x_VCRjnZf0"
        }
      ],
      "services": {
        "appinvite_service": {
          "other_platform_oauth_client": [
            {
              "client_id": "403090252778-22pv9spk76snfjin64oe5v0gi8vrfmvo.apps.googleusercontent.com",
              "client_type": 3
            }
          ]
        }
      }
    }
  ],
  "configuration_version": "1"
}